cmessage/__init__.py
cmessage/cmessage.py
cmessage-0.2.5.dist-info/METADATA
cmessage-0.2.5.dist-info/WHEEL
cmessage-0.2.5.dist-info/top_level.txt
cmessage-0.2.5.dist-info/RECORD
